zretry.py
zretry-0.1.1.dist-info/LICENSE
zretry-0.1.1.dist-info/METADATA
zretry-0.1.1.dist-info/WHEEL
zretry-0.1.1.dist-info/top_level.txt
zretry-0.1.1.dist-info/RECORD
